olinkform/__init__.py
olinkform/olinkform.py
olinkform/parser.py
olinkform-0.5.0.dist-info/AUTHORS.rst
olinkform-0.5.0.dist-info/LICENSE
olinkform-0.5.0.dist-info/METADATA
olinkform-0.5.0.dist-info/WHEEL
olinkform-0.5.0.dist-info/top_level.txt
olinkform-0.5.0.dist-info/RECORD
