Metadata-Version: 2.1
Name: olinkform
Version: 0.5.0
Summary: The preprocessing lib for olink data
Home-page: https://github.com/nehcgnay/olinkform
Author: Yang Chen
Author-email: yang.chen@scilifelab.se
License: MIT license
Keywords: olinkform
Platform: UNKNOWN
Classifier: Development Status :: 2 - Pre-Alpha
Classifier: Intended Audience :: Developers
Classifier: License :: OSI Approved :: MIT License
Classifier: Natural Language :: English
Classifier: Programming Language :: Python :: 3
Classifier: Programming Language :: Python :: 3.5
Classifier: Programming Language :: Python :: 3.6
Classifier: Programming Language :: Python :: 3.7
Classifier: Programming Language :: Python :: 3.8
Requires-Python: >=3.5
Requires-Dist: numpy (>=1.16.0)
Requires-Dist: pandas (>=0.25.0)
Requires-Dist: xlrd (>=1.0.0)
